compfile/__init__.py
compfile-0.0.3.dist-info/METADATA
compfile-0.0.3.dist-info/RECORD
compfile-0.0.3.dist-info/WHEEL
compfile-0.0.3.dist-info/top_level.txt
